rtl/ALU.v
module ALU(
    input [31:0]in0, in1,
    input [3:0]ALU_op,
    output reg [31:0]result,
    output zero_flag
    );

    parameter ADD_op = 4'b0000;
    parameter SUB_op = 4'b0001;
    parameter AND_op = 4'b0010;
    parameter OR_op = 4'b0011;
    parameter XOR_op = 4'b0100;
    parameter SLTU_op = 4'b0101;
    parameter SLT_op = 4'b0110;
    parameter SLL_op = 4'b0111;
    parameter SRL_op = 4'b1000;
    parameter SRA_op = 4'b1001;

    always @(*) begin
        case (ALU_op)
            ADD_op: result = in0 + in1;
            SUB_op: result = in0 - in1;
            AND_op: result = in0 & in1;
            OR_op: result = in0 | in1;
            XOR_op: result = in0 ^ in1;
            SLT_op: result = ($signed(in0) < $signed(in1))? 1:0;
            SLTU_op: result = (in0 <in1)?1:0;
            SLL_op: result = in0 << in1[4:0];
            SRL_op: result = in0 >> in1[4:0];
            SRA_op: result = $signed(in0) >>> in1[4:0];
            default: result = 0;
        endcase
    end

    assign zero_flag = (result == 0);
endmodule

// Module Purpose:
// Performs all calculations
// Designed in combinational style so that it does not depend on clock and provides immediate results

tb/tb_ALU.v
`timescale 1ns/1ps
`include "rtl/ALU.v" 

module tb_ALU();
    reg [31:0]in0;
    reg [31:0]in1;
    reg [3:0]ALU_op;
    wire [31:0]result;
    wire zero_flag;

    ALU uut (
        .in0(in0),
        .in1(in1),
        .ALU_op(ALU_op),
        .result(result),
        .zero_flag(zero_flag)
        );

        initial begin
            $dumpfile("ALU_Waveform.vcd");
            $dumpvars(0, tb_ALU);

            ALU_op = 4'b0000; //Addition
            in0 = 32'h7FFFFFFF;
            in1 = 32'd1;
            #10;
            in0 = 32'hFFFFFFFF;
            in1 = 32'd1;
            #10;
            in0 = 32'h80000000;
            in1 = 32'h80000000;
            #10;

            ALU_op = 4'b0001; //Subtraction
            in0 = 32'h00000000;
            in1 = 32'h00000001;
            #10;
            in0 = 32'h80000000;
            in1 = 32'h00000001;
            #10;
            in0 = 32'h7FFFFFFF;
            in1 = 32'hFFFFFFFF;
            #10;
            ALU_op = 4'b0010; //AND
            in0 = 32'hFFFFFFFF;
            in1 = 32'h00000000;
            #10;
            in0 = 32'hAAAAAAAA;
            in1 = 32'h55555555;
            #10;
            in0 = 32'hF0F0F0F0;
            in1 = 32'h0F0F0F0F;
            #10;
            ALU_op = 4'b0011; //OR
            in0 = 32'hFFFFFFFF;
            in1 = 32'h00000000;
            #10;
            in0 = 32'hAAAAAAAA;
            in1 = 32'h55555555;
            #10;
            in0 = 32'hF0F0F0F0;
            in1 = 32'h0F0F0F0F;
            #10;
            ALU_op = 4'b0100; //XOR
            in0 = 32'hFFFFFFFF;
            in1 = 32'h00000000;
            #10;
            in0 = 32'hAAAAAAAA;
            in1 = 32'h55555555;
            #10;
            in0 = 32'hF0F0F0F0;
            in1 = 32'h0F0F0F0F;
            #10;
            ALU_op = 4'b0101; //SLTU
            in0 = 32'h00000001;
            in1 = 32'h00000002;
            #10;
            in0 = 32'hFFFFFFFF;
            in1 = 32'h00000001;
            #10;
            in0 = 32'h7FFFFFFF;
            in1 = 32'h80000000;
            #10;
            ALU_op = 4'b0110; //SLT
            in0 = 32'h00000001;
            in1 = 32'h00000002;
            #10;
            in0 = 32'hFFFFFFFF;
            in1 = 32'h00000001;
            #10;
            in0 = 32'h80000000;
            in1 = 32'h7FFFFFFF;
            #10;
            ALU_op = 4'b0111; //SLL
            in0 = 32'h00000001;
            in1 = 32'h00000002;
            #10;
            in0 = 32'h00000001;
            in1 = 32'h00000000;
            #10;
            in0 = 32'hF0000000;
            in1 = 32'h0F000000;
            #10;
            ALU_op = 4'b1000; //SRL
            in0 = 32'h80000000;
            in1 = 32'hC0000000;
            #10;
            in0 = 32'h00000001;
            in1 = 32'h00000000;
            #10;
            in0 = 32'hF0000000;
            in1 = 32'h0F000000;
            #10;
            ALU_op = 4'b1001; //SRA
            in0 = 32'h80000000;
            in1 = 32'hC0000000;
            #10;
            in0 = 32'hFFFFFFFF;
            in1 = 32'hFFFFFFFF;
            #10;
            in0 = 32'hF0000000;
            in1 = 32'hFF000000;
            #10;
            $finish;
        end
endmodule;

ALU_Waveform.vcd
$date
	Fri Dec 12 14:37:28 2025
$end
$version
	Icarus Verilog
$end
$timescale
	1ps
$end
$scope module tb_ALU $end
$var wire 1 ! zero_flag $end
$var wire 32 " result [31:0] $end
$var reg 4 # ALU_op [3:0] $end
$var reg 32 $ in0 [31:0] $end
$var reg 32 % in1 [31:0] $end
$scope module uut $end
$var wire 4 & ALU_op [3:0] $end
$var wire 32 ' in0 [31:0] $end
$var wire 32 ( in1 [31:0] $end
$var wire 1 ! zero_flag $end
$var parameter 4 ) ADD_op $end
$var parameter 4 * AND_op $end
$var parameter 4 + OR_op $end
$var parameter 4 , SLL_op $end
$var parameter 4 - SLTU_op $end
$var parameter 4 . SLT_op $end
$var parameter 4 / SRA_op $end
$var parameter 4 0 SRL_op $end
$var parameter 4 1 SUB_op $end
$var parameter 4 2 XOR_op $end
$var reg 32 3 result [31:0] $end
$upscope $end
$upscope $end
$enddefinitions $end
$comment Show the parameter values. $end
$dumpall
b100 2
b1 1
b1000 0
b1001 /
b110 .
b101 -
b111 ,
b11 +
b10 *
b0 )
$end
#0
$dumpvars
b10000000000000000000000000000000 3
b1 (
b1111111111111111111111111111111 '
b0 &
b1 %
b1111111111111111111111111111111 $
b0 #
b10000000000000000000000000000000 "
0!
$end
#10000
1!
b0 "
b0 3
b11111111111111111111111111111111 $
b11111111111111111111111111111111 '
#20000
b10000000000000000000000000000000 %
b10000000000000000000000000000000 (
b10000000000000000000000000000000 $
b10000000000000000000000000000000 '
#30000
0!
b11111111111111111111111111111111 "
b11111111111111111111111111111111 3
b1 %
b1 (
b0 $
b0 '
b1 #
b1 &
#40000
b1111111111111111111111111111111 "
b1111111111111111111111111111111 3
b10000000000000000000000000000000 $
b10000000000000000000000000000000 '
#50000
b10000000000000000000000000000000 "
b10000000000000000000000000000000 3
b11111111111111111111111111111111 %
b11111111111111111111111111111111 (
b1111111111111111111111111111111 $
b1111111111111111111111111111111 '
#60000
1!
b0 "
b0 3
b0 %
b0 (
b11111111111111111111111111111111 $
b11111111111111111111111111111111 '
b10 #
b10 &
#70000
b1010101010101010101010101010101 %
b1010101010101010101010101010101 (
b10101010101010101010101010101010 $
b10101010101010101010101010101010 '
#80000
b1111000011110000111100001111 %
b1111000011110000111100001111 (
b11110000111100001111000011110000 $
b11110000111100001111000011110000 '
#90000
0!
b11111111111111111111111111111111 "
b11111111111111111111111111111111 3
b0 %
b0 (
b11111111111111111111111111111111 $
b11111111111111111111111111111111 '
b11 #
b11 &
#100000
b1010101010101010101010101010101 %
b1010101010101010101010101010101 (
b10101010101010101010101010101010 $
b10101010101010101010101010101010 '
#110000
b1111000011110000111100001111 %
b1111000011110000111100001111 (
b11110000111100001111000011110000 $
b11110000111100001111000011110000 '
#120000
b0 %
b0 (
b11111111111111111111111111111111 $
b11111111111111111111111111111111 '
b100 #
b100 &
#130000
b1010101010101010101010101010101 %
b1010101010101010101010101010101 (
b10101010101010101010101010101010 $
b10101010101010101010101010101010 '
#140000
b1111000011110000111100001111 %
b1111000011110000111100001111 (
b11110000111100001111000011110000 $
b11110000111100001111000011110000 '
#150000
b1 "
b1 3
b10 %
b10 (
b1 $
b1 '
b101 #
b101 &
#160000
1!
b0 "
b0 3
b1 %
b1 (
b11111111111111111111111111111111 $
b11111111111111111111111111111111 '
#170000
0!
b1 "
b1 3
b10000000000000000000000000000000 %
b10000000000000000000000000000000 (
b1111111111111111111111111111111 $
b1111111111111111111111111111111 '
#180000
b10 %
b10 (
b1 $
b1 '
b110 #
b110 &
#190000
b1 %
b1 (
b11111111111111111111111111111111 $
b11111111111111111111111111111111 '
#200000
b1111111111111111111111111111111 %
b1111111111111111111111111111111 (
b10000000000000000000000000000000 $
b10000000000000000000000000000000 '
#210000
b100 "
b100 3
b10 %
b10 (
b1 $
b1 '
b111 #
b111 &
#220000
b1 "
b1 3
b0 %
b0 (
#230000
b11110000000000000000000000000000 "
b11110000000000000000000000000000 3
b1111000000000000000000000000 %
b1111000000000000000000000000 (
b11110000000000000000000000000000 $
b11110000000000000000000000000000 '
#240000
b10000000000000000000000000000000 "
b10000000000000000000000000000000 3
b11000000000000000000000000000000 %
b11000000000000000000000000000000 (
b10000000000000000000000000000000 $
b10000000000000000000000000000000 '
b1000 #
b1000 &
#250000
b1 "
b1 3
b0 %
b0 (
b1 $
b1 '
#260000
b11110000000000000000000000000000 "
b11110000000000000000000000000000 3
b1111000000000000000000000000 %
b1111000000000000000000000000 (
b11110000000000000000000000000000 $
b11110000000000000000000000000000 '
#270000
b10000000000000000000000000000000 "
b10000000000000000000000000000000 3
b11000000000000000000000000000000 %
b11000000000000000000000000000000 (
b10000000000000000000000000000000 $
b10000000000000000000000000000000 '
b1001 #
b1001 &
#280000
b11111111111111111111111111111111 "
b11111111111111111111111111111111 3
b11111111111111111111111111111111 %
b11111111111111111111111111111111 (
b11111111111111111111111111111111 $
b11111111111111111111111111111111 '
#290000
b11110000000000000000000000000000 "
b11110000000000000000000000000000 3
b11111111000000000000000000000000 %
b11111111000000000000000000000000 (
b11110000000000000000000000000000 $
b11110000000000000000000000000000 '
