rtl/ALU.v
// Ye sab calculations perform karega
// Combinational design taaki fast rahe aur clock cycle ka wait na kare

module ALU(
    input [31:0]in0, in1,
    input [3:0]ALU_op,
    output reg [31:0]result,
    output zero_flag
    );

    parameter ADD_op = 4'b0000;
    parameter SUB_op = 4'b0001;
    parameter AND_op = 4'b0010;
    parameter OR_op = 4'b0011;
    parameter XOR_op = 4'b0100;
    parameter SLTU_op = 4'b0101;
    parameter SLT_op = 4'b0110;
    parameter SLL_op = 4'b0111;
    parameter SRL_op = 4'b1000;
    parameter SRA_op = 4'b1001;

    always @(*) begin
        case (ALU_op)
            ADD_op: result = in0 + in1;
            SUB_op: result = in0 - in1;
            AND_op: result = in0 & in1;
            OR_op: result = in0 | in1;
            XOR_op: result = in0 ^ in1;
            SLT_op: result = ($signed(in0) < $signed(in1))? 1:0;
            SLTU_op: result = (in0 <in1)?1:0;
            SLL_op: result = in0 << in1[4:0];
            SRL_op: result = in0 >> in1[4:0];
            SRA_op: result = $signed(in0) >>> in1[4:0];
            default: result = 0;
        endcase
    end

    assign zero_flag = (result == 0);
endmodule

rtl/EX_stage.v
module EX_stage(
    input [31:0]
        rs1_data, // from ID
        rs2_data,  // from ID
        imm, // from IG
        PC_out, // from IF
    input [3:0]
        alu_op, // from Decoder
    input
        alu_src, 
        branch, 
        jump, 
        jump_reg,
    output [31:0]
        ALU_result, // Result of ALU
        rs2_forward, // Value of rs2 will be forwarded to MEM stage
    output reg [31:0]
        PC_target,
    output reg
        Branch_taken // Whioch branch to be taken
    );

    wire [31:0] PC_plus_4;
    wire [31:0] PC_branch;
    wire [31:0] PC_jump;
    wire [31:0] PC_jump_reg;

    reg [31:0] second_im1;

    wire ALU_flag;

    assign PC_plus_4 = PC_out + 4;
    assign PC_branch = PC_out + imm;
    assign PC_jump = PC_out + imm;
    assign PC_jump_reg = rs1_data + imm;

    assign rs2_forward = rs2_data;

    always @(*)begin
        case(alu_src)
            1'b1: second_im1 = imm;
            1'b0: second_im1 = rs2_data;
        endcase
    end

    always @(*)begin
        Branch_taken = 0;
        PC_target = PC_plus_4;

        if (jump_reg)begin
            PC_target = PC_jump_reg;
            Branch_taken = 1;
        end else if (jump)begin
            PC_target = PC_jump;
            Branch_taken = 1;
        end else if (branch && ALU_flag)begin
            PC_target = PC_branch;
            Branch_taken = 1;
        end
    end

    ALU ALU_Block (
        .in0(rs1_data),
        .in1(second_im1),
        .ALU_op(alu_op),
        .result(ALU_result),
        .zero_flag(ALU_flag)
    );
endmodule;

tb/tb_EX.v
`timescale 1ns/1ps
`include "rtl/EX_stage.v"
`include "rtl/ALU.v"

module tb_EX();
    reg [31:0]rs1_data;
    reg [31:0]rs2_data;
    reg [31:0]imm;
    reg [31:0]PC_out;

    reg [3:0]alu_op;

    reg alu_src;
    reg jump;
    reg branch;
    reg jump_reg;

    wire [31:0] ALU_result;
    wire [31:0] rs2_forward;
    wire [31:0] PC_target;

    wire Branch_taken;

    EX_stage uut (
        .rs1_data(rs1_data),
        .rs2_data(rs2_data),
        .imm(imm),
        .PC_out(PC_out),
        .alu_op(alu_op),
        .alu_src(alu_src),
        .jump(jump),
        .branch(branch),
        .jump_reg(jump_reg),
        .ALU_result(ALU_result),
        .rs2_forward(rs2_forward),
        .PC_target(PC_target),
        .Branch_taken(Branch_taken)    
    );

    initial begin
        $dumpfile("EX_waveform.vcd");
        $dumpvars(0, tb_EX);


        // R type
        rs1_data = 10;
        rs2_data = 7;
        alu_src = 0;
        alu_op = 4'b0000; // ADD
        branch = 0;
        jump = 0;
        jump_reg = 0;
        PC_out = 100;
        #20;

        // I type
        alu_src = 1;
        imm = 5;
        #20;

        // Branch not taken
        imm = 16;
        alu_src = 0;
        alu_op = 4'b0001; // SUB
        branch = 1;
        #20;

        // Branch taken
        rs2_data = 10; // 10 - 10 = 0
        #20;

        // JAL
        imm = 32;
        jump = 1;
        PC_out = 100;
        #20;

        // JALR
        rs1_data = 200;
        imm = 12;
        jump_reg = 1;
        jump = 0;
        branch = 0;
        #20;

        // Priority test
        imm = 8;
        branch = 1;
        jump = 1;
        PC_out = 50;
        rs1_data = 5;
        rs2_data = 5;
        #20;

        //Default case
        branch = 0;
        jump = 0;
        jump_reg = 0;
        PC_out = 32;
        #20;

        $finish;
    end
endmodule;

EX_waveform.vcd
$date
	Tue Jan  6 20:50:32 2026
$end
$version
	Icarus Verilog
$end
$timescale
	1ps
$end
$scope module tb_EX $end
$var wire 32 ! rs2_forward [31:0] $end
$var wire 32 " PC_target [31:0] $end
$var wire 1 # Branch_taken $end
$var wire 32 $ ALU_result [31:0] $end
$var reg 32 % PC_out [31:0] $end
$var reg 4 & alu_op [3:0] $end
$var reg 1 ' alu_src $end
$var reg 1 ( branch $end
$var reg 32 ) imm [31:0] $end
$var reg 1 * jump $end
$var reg 1 + jump_reg $end
$var reg 32 , rs1_data [31:0] $end
$var reg 32 - rs2_data [31:0] $end
$scope module uut $end
$var wire 32 . PC_out [31:0] $end
$var wire 4 / alu_op [3:0] $end
$var wire 1 ' alu_src $end
$var wire 1 ( branch $end
$var wire 32 0 imm [31:0] $end
$var wire 1 * jump $end
$var wire 1 + jump_reg $end
$var wire 32 1 rs1_data [31:0] $end
$var wire 32 2 rs2_data [31:0] $end
$var wire 32 3 rs2_forward [31:0] $end
$var wire 32 4 PC_plus_4 [31:0] $end
$var wire 32 5 PC_jump_reg [31:0] $end
$var wire 32 6 PC_jump [31:0] $end
$var wire 32 7 PC_branch [31:0] $end
$var wire 32 8 ALU_result [31:0] $end
$var wire 1 9 ALU_flag $end
$var reg 1 # Branch_taken $end
$var reg 32 : PC_target [31:0] $end
$var reg 32 ; second_im1 [31:0] $end
$scope module ALU_Block $end
$var wire 4 < ALU_op [3:0] $end
$var wire 32 = in0 [31:0] $end
$var wire 32 > in1 [31:0] $end
$var wire 1 9 zero_flag $end
$var parameter 4 ? ADD_op $end
$var parameter 4 @ AND_op $end
$var parameter 4 A OR_op $end
$var parameter 4 B SLL_op $end
$var parameter 4 C SLTU_op $end
$var parameter 4 D SLT_op $end
$var parameter 4 E SRA_op $end
$var parameter 4 F SRL_op $end
$var parameter 4 G SUB_op $end
$var parameter 4 H XOR_op $end
$var reg 32 I result [31:0] $end
$upscope $end
$upscope $end
$upscope $end
$enddefinitions $end
$comment Show the parameter values. $end
$dumpall
b100 H
b1 G
b1000 F
b1001 E
b110 D
b101 C
b111 B
b11 A
b10 @
b0 ?
$end
#0
$dumpvars
b10001 I
b111 >
b1010 =
b0 <
b111 ;
b1101000 :
09
b10001 8
bx 7
bx 6
bx 5
b1101000 4
b111 3
b111 2
b1010 1
bx 0
b0 /
b1100100 .
b111 -
b1010 ,
0+
0*
bx )
0(
0'
b0 &
b1100100 %
b10001 $
0#
b1101000 "
b111 !
$end
#20000
b1111 $
b1111 8
b1111 I
b101 ;
b101 >
b1101001 7
b1101001 6
b1111 5
b101 )
b101 0
1'
#40000
b11 $
b11 8
b11 I
b111 ;
b111 >
1(
b1 &
b1 /
b1 <
0'
b1110100 7
b1110100 6
b11010 5
b10000 )
b10000 0
#60000
1#
b1110100 "
b1110100 :
19
b0 $
b0 8
b0 I
b1010 ;
b1010 >
b1010 !
b1010 3
b1010 -
b1010 2
#80000
b10000100 "
b10000100 :
1#
1*
b10000100 7
b10000100 6
b101010 5
b100000 )
b100000 0
#100000
b11010100 "
b11010100 :
1#
09
b10111110 $
b10111110 8
b10111110 I
0(
0*
1+
b1110000 7
b1110000 6
b1100 )
b1100 0
b11010100 5
b11001000 ,
b11001000 1
b11001000 =
#120000
19
b0 $
b0 8
b0 I
b101 ;
b101 >
b1101 "
b1101 :
1#
b101 !
b101 3
b101 -
b101 2
b101 ,
b101 1
b101 =
b110110 4
b110010 %
b110010 .
1*
1(
b111010 7
b111010 6
b1101 5
b1000 )
b1000 0
#140000
b100100 "
b100100 :
0#
b100100 4
b101000 7
b101000 6
b100000 %
b100000 .
0+
0*
0(
