rtl/Instruction_mem.v
// Iska kaam hai ki ye PC ka diya hua address input lega, aur output karega ki us address pe kaunsa instruction stored hai
// Iska asynchronous hona critical hai taki jaise hi PC ka address change hota hai, isko immediately naya instruction output krna hai

module Instruction_mem(
    input [31:0]PC_address,
    output [31:0]IM_instruction
    );

    reg [31:0]mem[255:0]; //32 bit registers jinki length 256 bits tak hai. Choosing 256 was purely a design choice. Width however was fixed at 32.

    assign IM_instruction = mem[PC_address[9:2]]; // Kyuki 32 bit register hai, to next address hamesha increament of 4 me aaega. To LSB ki 2 bits hamesha 00 rahengi. Now, 256 = 2^8 isliye we went from 2 to 9 

endmodule;

rtl/PC.v
module PC(
    input clk, rst,
    input [31:0]PC_in,
    input [1:0]PC_op,
    output reg [31:0]PC_out
    );

    parameter INCREAMENT = 2'b00;
    parameter LOAD = 2'b01;

    always @(posedge clk or posedge rst) begin
        if (rst) begin
            PC_out <= 0;
        end else begin
            case (PC_op)
                INCREAMENT: PC_out <= PC_out + 4;
                LOAD: PC_out <= PC_in;
                default: PC_out <= PC_out;
            endcase
        end
    end
endmodule;

// Module Purpose:
// Stores the address of the next instruction to be performed
// Sends this instruction to instruction memory on every rising clock pulse
// THree tasks:
// 1) Increament (By 4 because of 32 bit design (8 x 4 = 32))
// 2) Load (Output the current input)
// 3) Stall (Nothing changes in output)

fetch_stage.v
// Iska bas ek purpose hai, to connect PC and Instruction memory together

module fetch_stage (
    input clk, rst,
    input [31:0]PC_in, // Ye address jump or branch me load hoga
    input [1:0]PC_op,
    output [31:0]Instruction_out, // Instruction jo fetch hua hai, this will come from IM_Instruction
    output [31:0]PC_out, // Current instruction ka address 
    );

    PC PC_module (
        .clk(clk),
        .rst(rst),
        .PC_in(PC_in),
        .PC_op(PC_op),
        .PC_out(PC_out)
        );
    Instruction_mem Instruction_module (
        .IM_instruction(Instruction_out),
        .PC_address(PC_out)
        );
endmodule

tb/tb_fetch_stage.v
`timescale 1ns/1ps
`include "rtl/fetch_stage.v"
`include "rtl/PC.v"
`include "rtl/Instruction_mem.v"

module tb_fetch_stage();
    reg clk;
    reg rst;
    reg [31:0]PC_in;
    reg [1:0]PC_op;
    wire [31:0]Instruction_out;
    wire [31:0]PC_out;

    fetch_stage uut (
        .clk(clk),
        .rst(rst),
        .PC_in(PC_in),
        .PC_op(PC_op),
        .Instruction_out(Instruction_out),
        .PC_out(PC_out)
        );

        initial clk = 1'b0;

        always #5 clk = ~clk;

        initial begin
            $dumpfile("fetch_stage_waveform.vcd");
            $dumpvars(0, tb_fetch_stage);

            rst = 1'b1;
            PC_op = 2'b00; //Increment
            PC_in = 32'h0000_0000;
            uut.Instruction_module.mem[0] = 32'h00000013;
            uut.Instruction_module.mem[1] = 32'h00108093;
            uut.Instruction_module.mem[2] = 32'h00310113;
            uut.Instruction_module.mem[3] = 32'h00a18193;
            #12;
            rst = 1'b0;
            #8;

            PC_op = 2'b00; //Increment
            #20;

            PC_op = 2'b01; //Load
            PC_in = 32'h0000_0014;
            #10;

            PC_op = 2'b10; //Hold
            #10;

            PC_op = 2'b00; //Increament
            #20;

            PC_op = 2'b01; //Load
            PC_in = 32'h0000_00FC;
            #10;

            PC_op = 2'b00; //Increament
            #10;

            rst = 1'b1;
            #10;
            rst = 1'b0;
            #10;

            $finish;
        end
endmodule;

fetch_stage_waveform.vcd
$date
	Fri Dec 12 15:34:01 2025
$end
$version
	Icarus Verilog
$end
$timescale
	1ps
$end
$scope module tb_fetch_stage $end
$var wire 32 ! PC_out [31:0] $end
$var wire 32 " Instruction_out [31:0] $end
$var reg 32 # PC_in [31:0] $end
$var reg 2 $ PC_op [1:0] $end
$var reg 1 % clk $end
$var reg 1 & rst $end
$scope module uut $end
$var wire 32 ' PC_in [31:0] $end
$var wire 2 ( PC_op [1:0] $end
$var wire 1 % clk $end
$var wire 1 & rst $end
$var wire 32 ) PC_out [31:0] $end
$var wire 32 * Instruction_out [31:0] $end
$scope module Instruction_module $end
$var wire 32 + IM_instruction [31:0] $end
$var wire 32 , PC_address [31:0] $end
$upscope $end
$scope module PC_module $end
$var wire 32 - PC_in [31:0] $end
$var wire 2 . PC_op [1:0] $end
$var wire 1 % clk $end
$var wire 1 & rst $end
$var parameter 2 / INCREAMENT $end
$var parameter 2 0 LOAD $end
$var reg 32 1 PC_out [31:0] $end
$upscope $end
$upscope $end
$upscope $end
$enddefinitions $end
$comment Show the parameter values. $end
$dumpall
b1 0
b0 /
$end
#0
$dumpvars
b0 1
b0 .
b0 -
b0 ,
b10011 +
b10011 *
b0 )
b0 (
b0 '
1&
0%
b0 $
b0 #
b10011 "
b0 !
$end
#5000
1%
#10000
0%
#12000
0&
#15000
b100001000000010010011 "
b100001000000010010011 *
b100001000000010010011 +
b100 !
b100 )
b100 ,
b100 1
1%
#20000
0%
#25000
b1100010000000100010011 "
b1100010000000100010011 *
b1100010000000100010011 +
b1000 !
b1000 )
b1000 ,
b1000 1
1%
#30000
0%
#35000
b101000011000000110010011 "
b101000011000000110010011 *
b101000011000000110010011 +
b1100 !
b1100 )
b1100 ,
b1100 1
1%
#40000
0%
b10100 #
b10100 '
b10100 -
b1 $
b1 (
b1 .
#45000
bx "
bx *
bx +
b10100 !
b10100 )
b10100 ,
b10100 1
1%
#50000
0%
b10 $
b10 (
b10 .
#55000
1%
#60000
0%
b0 $
b0 (
b0 .
#65000
b11000 !
b11000 )
b11000 ,
b11000 1
1%
#70000
0%
#75000
b11100 !
b11100 )
b11100 ,
b11100 1
1%
#80000
0%
b11111100 #
b11111100 '
b11111100 -
b1 $
b1 (
b1 .
#85000
b11111100 !
b11111100 )
b11111100 ,
b11111100 1
1%
#90000
0%
b0 $
b0 (
b0 .
#95000
b100000000 !
b100000000 )
b100000000 ,
b100000000 1
1%
#100000
b10011 "
b10011 *
b10011 +
b0 !
b0 )
b0 ,
b0 1
0%
1&
#105000
1%
#110000
0%
0&
#115000
b100001000000010010011 "
b100001000000010010011 *
b100001000000010010011 +
b100 !
b100 )
b100 ,
b100 1
1%
