rtl/decoder_stage.v
module decoder_stage(
    input [31:0]
        instruction, // Taken from isntruction ememory
    output [4:0]
        rs1_addr,
        rs2_addr, 
        rd_addr,
    output reg [3:0]
        alu_op, // Which action to perform
    output reg
        reg_write, // 1: write
        alu_src, // 0: uses rs2 adder v/s 1: uses imm value
        mem_read, // 1: read from data memory
        mem_write, // 1: write to data memory
        mem_to_reg, // What gets written into rd, 0: ALU output or 1: data memory output
        branch, // 1: conditional branch
        jump, // 1: unconditional jump
        jump_reg // 1: jump depends on register
    );

    wire [6:0]op_code;
    wire [2:0]funct3;
    wire [6:0]funct7;

    // Based on official specificaitons:
    assign op_code = instruction[6:0];
    assign rd_addr = instruction[11:7];
    assign funct3 = instruction[14:12];
    assign rs1_addr = instruction[19:15];
    assign rs2_addr = instruction[24:20];
    assign funct7 = instruction[31:25];

    // same as my immediate generator
    parameter OP_IMM = 7'b0010011;
    parameter LOAD = 7'b0000011;
    parameter JALR = 7'b1100111;
    parameter STORE = 7'b0100011;
    parameter BRANCH = 7'b1100011;
    parameter LUI = 7'b0110111;
    parameter AUIPC = 7'b0010111;
    parameter JAL = 7'b1101111;
    parameter OP = 7'b0110011;

    // control decisions now:
    always @(*)begin
        reg_write = 0;
        alu_src = 0;
        alu_op = 0;
        mem_read = 0;
        mem_write = 0;
        mem_to_reg = 0;
        branch = 0;
        jump = 0;
        jump_reg = 0;
        case (op_code)
            OP: begin
                reg_write = 1; // read rs1 rs2 and writw the redult to rd

                case (funct3)
                    3'b000: begin // ADD and SUB
                        if (funct7 == 7'b0100000)begin
                            alu_op = 4'b0001; // SUB
                        end else begin
                            alu_op = 4'b0000; // ADD
                        end
                    end

                    3'b111: alu_op = 4'b0010; // AND
                    3'b110: alu_op = 4'b0011; // OR
                    3'b100: alu_op = 4'b0100; // XOR

                    3'b001: alu_op = 4'b0111; // SLL
                    3'b101: begin // SRL and SRA
                        if (funct7 == 7'b0100000)begin
                            alu_op = 4'b1001; // SRA
                        end else begin
                            alu_op = 4'b1000; // SRL
                        end
                    end

                    3'b010: alu_op = 4'b0110; // SLT
                    3'b011: alu_op = 4'b0101; // SLTU

                    default: alu_op = 4'b0000;
                endcase

            end
            OP_IMM: begin
                reg_write = 1; // write resukt into rd
                alu_src = 1; // use imm value
            end
            LOAD: begin // alu compute address = rs1 + imm
                reg_write = 1; // write result into rd
                alu_src = 1; // use imm value
                mem_read = 1; // read value at memory 
                mem_to_reg = 1; // data memory output gets written into rd
            end
            STORE: begin
                alu_src = 1; // use imm
                mem_write = 1; // write into data memory
            end
            BRANCH: begin
                branch = 1; // conditional pc update by comparing rs1 and rs2
            end
            JAL: begin
                reg_write = 1; // write ot rd
                alu_src = 1; // use imm value
                jump = 1; // unconditional jump
            end
            JALR: begin
                reg_write = 1; // give PC + 4 to rd
                alu_src = 1; // use imm
                jump_reg = 1;
            end
            LUI: begin
                reg_write = 1; // rd = imm << 12
                alu_src = 1;
            end
            AUIPC: begin // rd = PC + (imm << 12)
                reg_write = 1;
                alu_src = 1;
            end
        endcase
    end
endmodule;

// Module Purpose:
// Takes in a 32 bit instruction and generates register addresses and control signals for ALU, PC, Memory and Register file
// Decides what an instruction means, not it's execution

tb/tb_ID.v
`timescale 1ns/1ps
`include "rtl/decoder_stage.v"

module tb_ID();
    reg [31:0]instruction;
    wire [4:0]rs1_addr;
    wire [4:0]rs2_addr;
    wire [4:0]rd_addr;
    wire [3:0]alu_op;
    wire reg_write;
    wire alu_src;
    wire mem_read;
    wire mem_write;
    wire mem_to_reg;
    wire branch;
    wire jump;
    wire jump_reg;

    decoder_stage uut (
        .instruction(instruction),
        .rs1_addr(rs1_addr),
        .rs2_addr(rs2_addr),
        .rd_addr(rd_addr),
        .alu_op(alu_op),
        .reg_write(reg_write),
        .alu_src(alu_src),
        .mem_read(mem_read),
        .mem_write(mem_write),
        .mem_to_reg(mem_to_reg),
        .branch(branch),
        .jump(jump),
        .jump_reg(jump_reg)
    );

    initial begin
        $dumpfile("ID_waveform.vcd");
        $dumpvars(0, tb_ID);

        instruction = 32'h007302b3; // add x5, x6, x7 -> R type
        #10;
        instruction = 32'h00a48433; // add x8, x9, x10 -> R Type
        #10;
        instruction = 32'h00530293; // addi x5, x6, 5 -> I Type
        #10;
        instruction = 32'hfff10093; // addi x1, x2, -1 -> I type
        #10;
        instruction = 32'h0081a283; // lw x5, 8(x3) -> I Type
        #10;
        instruction = 32'h0040a623; // sw x4, 12(x1) -> S type
        #10;
        instruction = 32'h00208263; // beq x1, x2, 4 -> B type
        #10;
        instruction = 32'h008000ef; // jal x1, 8 -> J type
        #10;
        instruction = 32'h006200e7; // jalr x1, 6(x4) -> J type
        #10;
        instruction = 32'h123453b7; // lui x7, 0x12345 -> U type
        #10;
        instruction = 32'h00010197; // auipc x3, 0x10 -> U type
        #10;
        instruction = 32'h00000000; // Default
        #10;

        $finish;
    end
endmodule;

ID_waveform.vcd
$date
	Tue Dec 16 14:12:49 2025
$end
$version
	Icarus Verilog
$end
$timescale
	1ps
$end
$scope module tb_ID $end
$var wire 5 ! rs2_addr [4:0] $end
$var wire 5 " rs1_addr [4:0] $end
$var wire 1 # reg_write $end
$var wire 5 $ rd_addr [4:0] $end
$var wire 1 % mem_write $end
$var wire 1 & mem_to_reg $end
$var wire 1 ' mem_read $end
$var wire 1 ( jump_reg $end
$var wire 1 ) jump $end
$var wire 1 * branch $end
$var wire 1 + alu_src $end
$var wire 4 , alu_op [3:0] $end
$var reg 32 - instruction [31:0] $end
$scope module uut $end
$var wire 32 . instruction [31:0] $end
$var wire 5 / rs2_addr [4:0] $end
$var wire 5 0 rs1_addr [4:0] $end
$var wire 5 1 rd_addr [4:0] $end
$var wire 7 2 op_code [6:0] $end
$var wire 7 3 funct7 [6:0] $end
$var wire 3 4 funct3 [2:0] $end
$var parameter 7 5 AUIPC $end
$var parameter 7 6 BRANCH $end
$var parameter 7 7 JAL $end
$var parameter 7 8 JALR $end
$var parameter 7 9 LOAD $end
$var parameter 7 : LUI $end
$var parameter 7 ; OP $end
$var parameter 7 < OP_IMM $end
$var parameter 7 = STORE $end
$var reg 4 > alu_op [3:0] $end
$var reg 1 + alu_src $end
$var reg 1 * branch $end
$var reg 1 ) jump $end
$var reg 1 ( jump_reg $end
$var reg 1 ' mem_read $end
$var reg 1 & mem_to_reg $end
$var reg 1 % mem_write $end
$var reg 1 # reg_write $end
$upscope $end
$upscope $end
$enddefinitions $end
$comment Show the parameter values. $end
$dumpall
b100011 =
b10011 <
b110011 ;
b110111 :
b11 9
b1100111 8
b1101111 7
b1100011 6
b10111 5
$end
#0
$dumpvars
b0 >
b0 4
b0 3
b110011 2
b101 1
b110 0
b111 /
b11100110000001010110011 .
b11100110000001010110011 -
b0 ,
0+
0*
0)
0(
0'
0&
0%
b101 $
1#
b110 "
b111 !
$end
#10000
b1000 $
b1000 1
b1001 "
b1001 0
b1010 !
b1010 /
b101001001000010000110011 -
b101001001000010000110011 .
#20000
1+
1#
b10011 2
b101 $
b101 1
b110 "
b110 0
b101 !
b101 /
b10100110000001010010011 -
b10100110000001010010011 .
#30000
b1 $
b1 1
b10 "
b10 0
b11111 !
b11111 /
b1111111 3
b11111111111100010000000010010011 -
b11111111111100010000000010010011 .
#40000
1&
1'
1+
1#
b11 2
b101 $
b101 1
b10 4
b11 "
b11 0
b1000 !
b1000 /
b0 3
b100000011010001010000011 -
b100000011010001010000011 .
#50000
1%
0&
0'
1+
0#
b100011 2
b1100 $
b1100 1
b1 "
b1 0
b100 !
b100 /
b10000001010011000100011 -
b10000001010011000100011 .
#60000
1*
0%
0+
b1100011 2
b100 $
b100 1
b0 4
b10 !
b10 /
b1000001000001001100011 -
b1000001000001001100011 .
#70000
1)
1+
1#
0*
b1101111 2
b1 $
b1 1
b0 "
b0 0
b1000 !
b1000 /
b100000000000000011101111 -
b100000000000000011101111 .
#80000
1(
0)
1+
1#
b1100111 2
b100 "
b100 0
b110 !
b110 /
b11000100000000011100111 -
b11000100000000011100111 .
#90000
0(
1+
1#
b110111 2
b111 $
b111 1
b101 4
b1000 "
b1000 0
b11 !
b11 /
b1001 3
b10010001101000101001110110111 -
b10010001101000101001110110111 .
#100000
1+
1#
b10111 2
b11 $
b11 1
b0 4
b10 "
b10 0
b0 !
b0 /
b0 3
b10000000110010111 -
b10000000110010111 .
#110000
0+
0#
b0 2
b0 $
b0 1
b0 "
b0 0
b0 -
b0 .
