rtl/ImmediateGenerator.v
module ImmediateGenerator(
    input [31:0]instruction, // Took from instruction memory
    output reg [31:0]imm // Given to ALU etc
    );

    wire [6:0]instruct_type = instruction[6:0]; // 7 Bits because thats the way RISC-V are designed. TO scale, this provides 128 different operations to add.
    // I am going to use the classic op code mapping:

    parameter OP_IMM = 7'b0010011;
    parameter LOAD = 7'b0000011;
    parameter JALR = 7'b1100111;
    parameter STORE = 7'b0100011;
    parameter BRANCH = 7'b1100011;
    parameter LUI = 7'b0110111;
    parameter AUIPC = 7'b0010111;
    parameter JAL = 7'b1101111;
    parameter OP = 7'b0110011;

    always @(*)begin
        imm = 0; // I did this for safety reasonds
        case (instruct_type)
        OP_IMM: begin // I Type
            imm[11:0] = instruction[31:20]; // I did all the assigning using the op code table provided in official RISC-V documents
            imm[31:12] = instruction[31]; // Sign extension
        end
        LOAD: begin // I Type
            imm[11:0] = instruction[31:20];
            imm[31:12] = instruction[31];
        end
        JALR: begin // I Type
            imm[11:0] = instruction[31:20];
            imm[31:12] = instruction[31];
        end
        STORE: begin // S Type
            imm[11:5] = instruction[31:25];
            imm[4:0] = instruction[11:7];
            imm[31:12] = instruction[31];
        end
        BRANCH: begin // B Type
            imm[12] = instruction[31];
            imm[10:5] = instruction[30:25];
            imm[4:1] = instruction[11:8];
            imm[11] = instruction[7];
            imm[31:13] = instruction[31];
            imm = imm << 1;
        end
        LUI: imm[31:12] = instruction[31:12]; // U Type
        AUIPC: imm[31:12] = instruction[31:12]; // U Type
        JAL: begin // J Type
            imm[20] = instruction[31];
            imm[10:1] = instruction[30:21];
            imm[11] = instruction[20];
            imm[19:12] = instruction[19:12];
            imm[31:21] = instruction[31];
            imm = imm << 1;
        end
        default: imm = 0; // R Type
        endcase
    end
endmodule;

// Module purpose:
// Extracts and constructs 32 bit signed immediate values from a 32-bit instruction
// Purely combinational

rtl/decoder_stage.v
module decoder_stage(
    input [31:0]
        instruction, // Taken from isntruction ememory
    output [4:0]
        rs1_addr,
        rs2_addr, 
        rd_addr,
    output reg [3:0]
        alu_op, // Which action to perform
    output reg
        reg_write, // 1: write
        alu_src, // 0: uses rs2 adder v/s 1: uses imm value
        mem_read, // 1: read from data memory
        mem_write, // 1: write to data memory
        mem_to_reg, // What gets written into rd, 0: ALU output or 1: data memory output
        branch, // 1: conditional branch
        jump, // 1: unconditional jump
        jump_reg // 1: jump depends on register
    );

    wire [6:0]op_code;
    wire [2:0]funct3;
    wire [6:0]funct7;

    // Based on official specificaitons:
    assign op_code = instruction[6:0];
    assign rd_addr = instruction[11:7];
    assign funct3 = instruction[14:12];
    assign rs1_addr = instruction[19:15];
    assign rs2_addr = instruction[24:20];
    assign funct7 = instruction[31:25];

    // same as my immediate generator
    parameter OP_IMM = 7'b0010011;
    parameter LOAD = 7'b0000011;
    parameter JALR = 7'b1100111;
    parameter STORE = 7'b0100011;
    parameter BRANCH = 7'b1100011;
    parameter LUI = 7'b0110111;
    parameter AUIPC = 7'b0010111;
    parameter JAL = 7'b1101111;
    parameter OP = 7'b0110011;

    // control decisions now:
    always @(*)begin
        reg_write = 0;
        alu_src = 0;
        alu_op = 0;
        mem_read = 0;
        mem_write = 0;
        mem_to_reg = 0;
        branch = 0;
        jump = 0;
        jump_reg = 0;
        case (op_code)
            OP: begin
                reg_write = 1; // read rs1 rs2 and writw the redult to rd

                case (funct3)
                    3'b000: begin // ADD and SUB
                        if (funct7 == 7'b0100000)begin
                            alu_op = 4'b0001; // SUB
                        end else begin
                            alu_op = 4'b0000; // ADD
                        end
                    end

                    3'b111: alu_op = 4'b0010; // AND
                    3'b110: alu_op = 4'b0011; // OR
                    3'b100: alu_op = 4'b0100; // XOR

                    3'b001: alu_op = 4'b0111; // SLL
                    3'b101: begin // SRL and SRA
                        if (funct7 == 7'b0100000)begin
                            alu_op = 4'b1001; // SRA
                        end else begin
                            alu_op = 4'b1000; // SRL
                        end
                    end

                    3'b010: alu_op = 4'b0110; // SLT
                    3'b011: alu_op = 4'b0101; // SLTU

                    default: alu_op = 4'b0000;
                endcase

            end
            OP_IMM: begin
                reg_write = 1; // write resukt into rd
                alu_src = 1; // use imm value
            end
            LOAD: begin // alu compute address = rs1 + imm
                reg_write = 1; // write result into rd
                alu_src = 1; // use imm value
                mem_read = 1; // read value at memory 
                mem_to_reg = 1; // data memory output gets written into rd
            end
            STORE: begin
                alu_src = 1; // use imm
                mem_write = 1; // write into data memory
            end
            BRANCH: begin
                branch = 1; // conditional pc update by comparing rs1 and rs2
            end
            JAL: begin
                reg_write = 1; // write ot rd
                alu_src = 1; // use imm value
                jump = 1; // unconditional jump
            end
            JALR: begin
                reg_write = 1; // give PC + 4 to rd
                alu_src = 1; // use imm
                jump_reg = 1;
            end
            LUI: begin
                reg_write = 1; // rd = imm << 12
                alu_src = 1;
            end
            AUIPC: begin // rd = PC + (imm << 12)
                reg_write = 1;
                alu_src = 1;
            end
        endcase
    end
endmodule;

// Module Purpose:
// Takes in a 32 bit instruction and generates register addresses and control signals for ALU, PC, Memory and Register file
// Decides what an instruction means, not it's execution

rtl/Reg32x32.v
module Reg32x32(
    input clk, rst, rd_we, // Write enable
    input [4:0] rs1_addr, rs2_addr, // Address of register sources 1 and 2. 5 bits because 2^5 = 32 so we need 5 bit op code
    input [4:0] rd_addr, // Register to be written on
    input [31:0] rd_wdata, // Write data
    output reg [31:0] rs1_data, rs2_data
    );

    reg [31:0]mem[0:31]; // 32x32 bit memory array
    integer i;

    always @(posedge clk or posedge rst)begin
        if (rst)begin
            for (i = 0; i < 32; i = i + 1)begin
                mem[i] <= 0;
            end
        end else begin
            if (rd_we == 1 && rd_addr != 0)begin
                mem[rd_addr] <= rd_wdata;
            end
        end
    end

    always @(*)begin
        rs1_data = (rs1_addr == 0)? 0 : mem[rs1_addr];
        rs2_data = (rs2_addr == 0)? 0 : mem[rs2_addr];
        mem[0] = 0;
    end
endmodule;

rtl/ID_stage.v
module ID_stage(
    input [31:0]instruction,
    input clk, rst,
    output [31:0]rs1_data, rs2_data, imm,
    output [4:0]rd_addr
    );

    wire [4:0]rs1_addr_decoder;
    wire [4:0]rs2_addr_decoder;
    wire [4:0]rd_addr_decoder;   

    assign rd_addr = rd_addr_decoder;

    Reg32x32 REGISTER(
        .clk(clk),
        .rst(rst),
        .rs1_addr(rs1_addr_decoder),
        .rs2_addr(rs2_addr_decoder),
        .rd_addr(rd_addr_decoder),
        .rs1_data(rs1_data),
        .rs2_data(rs2_data),
        .rd_we(1'b0),
        .rd_wdata(0)
    );
    decoder_stage DECODER(
        .instruction(instruction),
        .rs1_addr(rs1_addr_decoder),
        .rs2_addr(rs2_addr_decoder),
        .rd_addr(rd_addr_decoder)
    );
    ImmediateGenerator IMM_GENERATOR(
        .instruction(instruction),
        .imm(imm)
    );
endmodule;

tb/tb_ID.v
`timescale 1ns/1ps
`include "rtl/decoder_stage.v"
`include "rtl/ImmediateGenerator.v"
`include "rtl/Reg32x32.v"
`include "rtl/ID_stage.v"

module tb_ID();
    reg [31:0]instruction;
    reg clk;
    reg rst;
    wire [31:0]rs1_data;
    wire [31:0]rs2_data;
    wire [31:0]imm;
    wire [4:0]rd_addr;

    ID_stage uut (
        .instruction(instruction),
        .clk(clk),
        .rst(rst),
        .rs1_data(rs1_data),
        .rs2_data(rs2_data),
        .imm(imm),
        .rd_addr(rd_addr)
    );

    initial clk = 0;

    always #5 clk = ~clk;

    initial begin
        $dumpfile("ID_waveform.vcd");
        $dumpvars(0, tb_ID);

        rst = 1;
        instruction = 32'hFFFFFFFF;
        #12;

        rst = 0;
        #8;

        instruction = 32'h007302b3; // add x5, x6, x7 -> R type
        #20;
        instruction = 32'h00a48433; // add x8, x9, x10 -> R Type
        #20;
        instruction = 32'h00530293; // addi x5, x6, 5 -> I Type
        #20;
        instruction = 32'hfff10093; // addi x1, x2, -1 -> I type
        #20;
        instruction = 32'h0081a283; // lw x5, 8(x3) -> I Type
        #20;
        instruction = 32'h0040a623; // sw x4, 12(x1) -> S type
        #20;
        instruction = 32'h00208263; // beq x1, x2, 4 -> B type
        #20;
        instruction = 32'h008000ef; // jal x1, 8 -> J type
        #20;
        instruction = 32'h006200e7; // jalr x1, 6(x4) -> J type
        #20;
        instruction = 32'h123453b7; // lui x7, 0x12345 -> U type
        #20;
        instruction = 32'h00010197; // auipc x3, 0x10 -> U type
        #20;

        $finish;
    end
endmodule;

ID_waveform.vcd
$date
	Tue Dec 16 22:45:44 2025
$end
$version
	Icarus Verilog
$end
$timescale
	1ps
$end
$scope module tb_ID $end
$var wire 32 ! rs2_data [31:0] $end
$var wire 32 " rs1_data [31:0] $end
$var wire 5 # rd_addr [4:0] $end
$var wire 32 $ imm [31:0] $end
$var reg 1 % clk $end
$var reg 32 & instruction [31:0] $end
$var reg 1 ' rst $end
$scope module uut $end
$var wire 1 % clk $end
$var wire 32 ( instruction [31:0] $end
$var wire 5 ) rd_addr [4:0] $end
$var wire 1 ' rst $end
$var wire 32 * rs2_data [31:0] $end
$var wire 5 + rs2_addr_decoder [4:0] $end
$var wire 32 , rs1_data [31:0] $end
$var wire 5 - rs1_addr_decoder [4:0] $end
$var wire 5 . rd_addr_decoder [4:0] $end
$var wire 32 / imm [31:0] $end
$scope module DECODER $end
$var wire 32 0 instruction [31:0] $end
$var wire 5 1 rs2_addr [4:0] $end
$var wire 5 2 rs1_addr [4:0] $end
$var wire 5 3 rd_addr [4:0] $end
$var wire 7 4 op_code [6:0] $end
$var wire 7 5 funct7 [6:0] $end
$var wire 3 6 funct3 [2:0] $end
$var parameter 7 7 AUIPC $end
$var parameter 7 8 BRANCH $end
$var parameter 7 9 JAL $end
$var parameter 7 : JALR $end
$var parameter 7 ; LOAD $end
$var parameter 7 < LUI $end
$var parameter 7 = OP $end
$var parameter 7 > OP_IMM $end
$var parameter 7 ? STORE $end
$var reg 4 @ alu_op [3:0] $end
$var reg 1 A alu_src $end
$var reg 1 B branch $end
$var reg 1 C jump $end
$var reg 1 D jump_reg $end
$var reg 1 E mem_read $end
$var reg 1 F mem_to_reg $end
$var reg 1 G mem_write $end
$var reg 1 H reg_write $end
$upscope $end
$scope module IMM_GENERATOR $end
$var wire 32 I instruction [31:0] $end
$var wire 7 J instruct_type [6:0] $end
$var parameter 7 K AUIPC $end
$var parameter 7 L BRANCH $end
$var parameter 7 M JAL $end
$var parameter 7 N JALR $end
$var parameter 7 O LOAD $end
$var parameter 7 P LUI $end
$var parameter 7 Q OP $end
$var parameter 7 R OP_IMM $end
$var parameter 7 S STORE $end
$var reg 32 T imm [31:0] $end
$upscope $end
$scope module REGISTER $end
$var wire 1 % clk $end
$var wire 5 U rd_addr [4:0] $end
$var wire 32 V rd_wdata [31:0] $end
$var wire 1 W rd_we $end
$var wire 5 X rs1_addr [4:0] $end
$var wire 5 Y rs2_addr [4:0] $end
$var wire 1 ' rst $end
$var reg 32 Z rs1_data [31:0] $end
$var reg 32 [ rs2_data [31:0] $end
$var integer 32 \ i [31:0] $end
$upscope $end
$upscope $end
$upscope $end
$enddefinitions $end
$comment Show the parameter values. $end
$dumpall
b100011 S
b10011 R
b110011 Q
b110111 P
b11 O
b1100111 N
b1101111 M
b1100011 L
b10111 K
b100011 ?
b10011 >
b110011 =
b110111 <
b11 ;
b1100111 :
b1101111 9
b1100011 8
b10111 7
$end
#0
$dumpvars
b100000 \
b0 [
b0 Z
b11111 Y
b11111 X
0W
b0 V
b11111 U
b0 T
b1111111 J
b11111111111111111111111111111111 I
0H
0G
0F
0E
0D
0C
0B
0A
b0 @
b111 6
b1111111 5
b1111111 4
b11111 3
b11111 2
b11111 1
b11111111111111111111111111111111 0
b0 /
b11111 .
b11111 -
b0 ,
b11111 +
b0 *
b11111 )
b11111111111111111111111111111111 (
1'
b11111111111111111111111111111111 &
0%
b0 $
b11111 #
b0 "
b0 !
$end
#5000
b100000 \
1%
#10000
0%
#12000
0'
#15000
1%
#20000
1H
b110011 4
b101 #
b101 )
b101 .
b101 3
b101 U
b0 6
b110 -
b110 2
b110 X
b111 +
b111 1
b111 Y
b0 5
b110011 J
0%
b11100110000001010110011 &
b11100110000001010110011 (
b11100110000001010110011 0
b11100110000001010110011 I
#25000
1%
#30000
0%
#35000
1%
#40000
b1000 #
b1000 )
b1000 .
b1000 3
b1000 U
b1001 -
b1001 2
b1001 X
b1010 +
b1010 1
b1010 Y
0%
b101001001000010000110011 &
b101001001000010000110011 (
b101001001000010000110011 0
b101001001000010000110011 I
#45000
1%
#50000
0%
#55000
1%
#60000
1A
1H
b10011 4
b101 #
b101 )
b101 .
b101 3
b101 U
b110 -
b110 2
b110 X
b101 +
b101 1
b101 Y
b101 $
b101 /
b101 T
b10011 J
0%
b10100110000001010010011 &
b10100110000001010010011 (
b10100110000001010010011 0
b10100110000001010010011 I
#65000
1%
#70000
0%
#75000
1%
#80000
b1 #
b1 )
b1 .
b1 3
b1 U
b10 -
b10 2
b10 X
b11111 +
b11111 1
b11111 Y
b1111111 5
b11111111111111111111111111111111 $
b11111111111111111111111111111111 /
b11111111111111111111111111111111 T
0%
b11111111111100010000000010010011 &
b11111111111100010000000010010011 (
b11111111111100010000000010010011 0
b11111111111100010000000010010011 I
#85000
1%
#90000
0%
#95000
1%
#100000
1F
1E
1A
1H
b11 4
b101 #
b101 )
b101 .
b101 3
b101 U
b10 6
b11 -
b11 2
b11 X
b1000 +
b1000 1
b1000 Y
b0 5
b1000 $
b1000 /
b1000 T
b11 J
0%
b100000011010001010000011 &
b100000011010001010000011 (
b100000011010001010000011 0
b100000011010001010000011 I
#105000
1%
#110000
0%
#115000
1%
#120000
1G
0F
0E
1A
0H
b100011 4
b1100 #
b1100 )
b1100 .
b1100 3
b1100 U
b1 -
b1 2
b1 X
b100 +
b100 1
b100 Y
b1100 $
b1100 /
b1100 T
b100011 J
0%
b10000001010011000100011 &
b10000001010011000100011 (
b10000001010011000100011 0
b10000001010011000100011 I
#125000
1%
#130000
0%
#135000
1%
#140000
1B
0G
0A
b1100011 4
b100 #
b100 )
b100 .
b100 3
b100 U
b0 6
b10 +
b10 1
b10 Y
b1000 $
b1000 /
b1000 T
b1100011 J
0%
b1000001000001001100011 &
b1000001000001001100011 (
b1000001000001001100011 0
b1000001000001001100011 I
#145000
1%
#150000
0%
#155000
1%
#160000
1C
1A
1H
0B
b1101111 4
b1 #
b1 )
b1 .
b1 3
b1 U
b0 -
b0 2
b0 X
b1000 +
b1000 1
b1000 Y
b1000 $
b1000 /
b1000 T
b1101111 J
0%
b100000000000000011101111 &
b100000000000000011101111 (
b100000000000000011101111 0
b100000000000000011101111 I
#165000
1%
#170000
0%
#175000
1%
#180000
1D
0C
1A
1H
b1100111 4
b100 -
b100 2
b100 X
b110 +
b110 1
b110 Y
b110 $
b110 /
b110 T
b1100111 J
0%
b11000100000000011100111 &
b11000100000000011100111 (
b11000100000000011100111 0
b11000100000000011100111 I
#185000
1%
#190000
0%
#195000
1%
#200000
0D
1A
1H
b110111 4
b111 #
b111 )
b111 .
b111 3
b111 U
b101 6
b1000 -
b1000 2
b1000 X
b11 +
b11 1
b11 Y
b1001 5
b10010001101000101000000000000 $
b10010001101000101000000000000 /
b10010001101000101000000000000 T
b110111 J
0%
b10010001101000101001110110111 &
b10010001101000101001110110111 (
b10010001101000101001110110111 0
b10010001101000101001110110111 I
#205000
1%
#210000
0%
#215000
1%
#220000
1A
1H
b10111 4
b11 #
b11 )
b11 .
b11 3
b11 U
b0 6
b10 -
b10 2
b10 X
b0 +
b0 1
b0 Y
b0 5
b10000000000000000 $
b10000000000000000 /
b10000000000000000 T
b10111 J
0%
b10000000110010111 &
b10000000110010111 (
b10000000110010111 0
b10000000110010111 I
