rtl/ImmediateGenerator.v
module ImmediateGenerator(
    input [31:0]instruction, // Took from instruction memory
    output reg [31:0]imm // Given to ALU etc
    );

    wire [6:0]instruct_type = instruction[6:0]; // 7 Bits because thats the way RISC-V are designed. TO scale, this provides 128 different operations to add.
    // I am going to use the classic op code mapping:

    parameter OP_IMM = 7'b0010011;
    parameter LOAD = 7'b0000011;
    parameter JALR = 7'b1100111;
    parameter STORE = 7'b0100011;
    parameter BRANCH = 7'b1100011;
    parameter LUI = 7'b0110111;
    parameter AUIPC = 7'b0010111;
    parameter JAL = 7'b1101111;
    parameter OP = 7'b0110011;

    always @(*)begin
        imm = 0; // I did this for safety reasonds
        case (instruct_type)
        OP_IMM: begin // I Type
            imm[11:0] = instruction[31:20]; // I did all the assigning using the op code table provided in official RISC-V documents
            imm[31:12] = {20{instruction[31]}}; // Sign extension
        end
        LOAD: begin // I Type
            imm[11:0] = instruction[31:20];
            imm[31:12] = {20{instruction[31]}};
        end
        JALR: begin // I Type
            imm[11:0] = instruction[31:20];
            imm[31:12] = {20{instruction[31]}};
        end
        STORE: begin // S Type
            imm[11:5] = instruction[31:25];
            imm[4:0] = instruction[11:7];
            imm[31:12] = {20{instruction[31]}};
        end
        BRANCH: begin // B Type
            imm[12] = instruction[31];
            imm[10:5] = instruction[30:25];
            imm[4:1] = instruction[11:8];
            imm[11] = instruction[7];
            imm[31:13] = {19{instruction[31]}};
            imm = imm << 1; // Shifted because B and J type instructions store addresses in units of 2 bytes instead of 1.
        end
        LUI: imm[31:12] = instruction[31:12]; // U Type
        AUIPC: imm[31:12] = instruction[31:12]; // U Type
        JAL: begin // J Type
            imm[20] = instruction[31];
            imm[10:1] = instruction[30:21];
            imm[11] = instruction[20];
            imm[19:12] = instruction[19:12];
            imm[31:21] = {11{instruction[31]}};
        end
        default: imm = 0; // R Type
        endcase
    end
endmodule;

// Module purpose:
// Extracts and constructs 32 bit signed immediate values from a 32-bit instruction
// Purely combinational

tb/tb_IG.v
`timescale 1ns/1ps
`include "rtl/ImmediateGenerator.v"

module tb_IG();
    reg [31:0]instruction;
    wire [31:0]imm;

    ImmediateGenerator uut (
        .instruction(instruction),
        .imm(imm)
    );

    initial begin
        $dumpfile("IG_waveform.vcd");
        $dumpvars(0, tb_IG);

        instruction = 32'h00a10093; // addi x1 x2 10
        #20;

        instruction = 32'hfff10093; // addi x1 x2 -1
        #20;

        instruction = 32'hfe322c23; // sw x3, -8(x4)
        #20;

        instruction = 32'hfe208ee3; // beq x1, x2, -4
        #20;
        
        instruction = 32'h00208463; // beq x1, x2, 8
        #20;

        instruction = 32'h123452b7; // lui x5, 0x12345
        #20;

        instruction = 32'h008000ef; // jal x1, 8
        #20;

        instruction = 32'hff9ff0ef; // jal x1, -8
        #20;
        $finish;
    end
endmodule;

IG_waveform.vcd
$date
	Sun Dec 14 14:51:00 2025
$end
$version
	Icarus Verilog
$end
$timescale
	1ps
$end
$scope module tb_IG $end
$var wire 32 ! imm [31:0] $end
$var reg 32 " instruction [31:0] $end
$scope module uut $end
$var wire 32 # instruction [31:0] $end
$var wire 7 $ instruct_type [6:0] $end
$var parameter 7 % AUIPC $end
$var parameter 7 & BRANCH $end
$var parameter 7 ' JAL $end
$var parameter 7 ( JALR $end
$var parameter 7 ) LOAD $end
$var parameter 7 * LUI $end
$var parameter 7 + OP $end
$var parameter 7 , OP_IMM $end
$var parameter 7 - STORE $end
$var reg 32 . imm [31:0] $end
$upscope $end
$upscope $end
$enddefinitions $end
$comment Show the parameter values. $end
$dumpall
b100011 -
b10011 ,
b110011 +
b110111 *
b11 )
b1100111 (
b1101111 '
b1100011 &
b10111 %
$end
#0
$dumpvars
b1010 .
b10011 $
b101000010000000010010011 #
b101000010000000010010011 "
b1010 !
$end
#20000
b11111111111111111111111111111111 !
b11111111111111111111111111111111 .
b11111111111100010000000010010011 "
b11111111111100010000000010010011 #
#40000
b11111111111111111111111111111000 !
b11111111111111111111111111111000 .
b100011 $
b11111110001100100010110000100011 "
b11111110001100100010110000100011 #
#60000
b11111111111111111111111111111000 !
b11111111111111111111111111111000 .
b1100011 $
b11111110001000001000111011100011 "
b11111110001000001000111011100011 #
#80000
b10000 !
b10000 .
b1000001000010001100011 "
b1000001000010001100011 #
#100000
b10010001101000101000000000000 !
b10010001101000101000000000000 .
b110111 $
b10010001101000101001010110111 "
b10010001101000101001010110111 #
#120000
b1000 !
b1000 .
b1101111 $
b100000000000000011101111 "
b100000000000000011101111 #
#140000
b11111111111111111111111111111000 !
b11111111111111111111111111111000 .
b11111111100111111111000011101111 "
b11111111100111111111000011101111 #
