rtl/Reg32x32.v
module Reg32x32(
    input clk, rst, rd_we, // Write enable
    input [4:0] rs1_addr, rs2_addr, // Address of register sources 1 and 2. 5 bits because 2^5 = 32 so we need 5 bit op code
    input [4:0] rd_addr, // Register to be written on
    input [31:0] rd_wdata, // Write data
    output reg [31:0] rs1_data, rs2_data
    );

    reg [31:0]mem[0:31]; // 32x32 bit memory array
    integer i;

    always @(posedge clk or posedge rst)begin
        if (rst)begin
            for (i = 0; i < 32; i = i + 1)begin
                mem[i] <= 0;
            end
        end else begin
            if (rd_we == 1 && rd_addr != 0)begin
                mem[rd_addr] <= rd_wdata;
            end
        end
    end

    always @(*)begin
        rs1_data = (rs1_addr == 0)? 0 : mem[rs1_addr];
        rs2_data = (rs2_addr == 0)? 0 : mem[rs2_addr];
        mem[0] = 0;
    end
endmodule;

tb/tb_reg.v
`timescale 1ns/1ps
`include "rtl/Reg32x32.v"

module tb_reg();
    reg clk;
    reg rst;
    reg rd_we;
    reg [4:0] rs1_addr;
    reg [4:0] rs2_addr;
    reg [4:0] rd_addr;
    reg [31:0] rd_wdata;
    wire [31:0] rs1_data;
    wire [31:0] rs2_data;

    Reg32x32 uut (
        .clk(clk),
        .rst(rst),
        .rd_we(rd_we),
        .rs1_addr(rs1_addr),
        .rs2_addr(rs2_addr),
        .rd_addr(rd_addr),
        .rd_wdata(rd_wdata),
        .rs1_data(rs1_data),
        .rs2_data(rs2_data)
    );

    initial clk = 0;

    always #5 clk = ~clk;

    initial begin
        $dumpfile("reg_waveform.vcd");
        $dumpvars(0, tb_reg);

        rst = 1;

        rd_we = 0;

        rs1_addr = 0;
        rs2_addr = 0;

        rd_addr = 0;
        rd_wdata = 0;

        #12;

        rst = 0;
        #8;

        uut.mem[3] = 32'hABAB_ABAB;
        uut.mem[7] = 32'hBABA_BABA;
        uut.mem[10] = 32'h1111_1111;
        uut.mem[20] = 32'h2222_2222;
        #20;

        rs1_addr = 3;
        rs2_addr = 7;
        #20;

        rd_we = 1;
        rd_addr = 0;
        rd_wdata = 32'hFFFF_FFFF;
        #20;

        rs1_addr = 0;
        #20;

        rd_we = 0;
        rd_addr = 5;
        rd_wdata = 32'hABCD_ABCD;
        #20;

        rs1_addr = 5;
        #20;

        rd_we = 1;
        rd_addr = 5;
        rd_wdata = 32'hABCA_ABCA;
        #20;

        rs1_addr = 5;
        #20;

        rs1_addr = 10;
        rs2_addr = 20;
        #20;

        rd_addr = 8;
        rd_wdata = 32'h0101_0101;
        #20;

        rs1_addr = 8;
        #20;

        $finish;
    end
endmodule;

reg_waveform.vcd
$date
	Sat Dec 13 17:00:20 2025
$end
$version
	Icarus Verilog
$end
$timescale
	1ps
$end
$scope module tb_reg $end
$var wire 32 ! rs2_data [31:0] $end
$var wire 32 " rs1_data [31:0] $end
$var reg 1 # clk $end
$var reg 5 $ rd_addr [4:0] $end
$var reg 32 % rd_wdata [31:0] $end
$var reg 1 & rd_we $end
$var reg 5 ' rs1_addr [4:0] $end
$var reg 5 ( rs2_addr [4:0] $end
$var reg 1 ) rst $end
$scope module uut $end
$var wire 1 # clk $end
$var wire 5 * rd_addr [4:0] $end
$var wire 32 + rd_wdata [31:0] $end
$var wire 1 & rd_we $end
$var wire 5 , rs1_addr [4:0] $end
$var wire 5 - rs2_addr [4:0] $end
$var wire 1 ) rst $end
$var reg 32 . rs1_data [31:0] $end
$var reg 32 / rs2_data [31:0] $end
$var integer 32 0 i [31:0] $end
$upscope $end
$upscope $end
$enddefinitions $end
$comment Show the parameter values. $end
$dumpall
$end
#0
$dumpvars
b100000 0
b0 /
b0 .
b0 -
b0 ,
b0 +
b0 *
1)
b0 (
b0 '
0&
b0 %
b0 $
0#
b0 "
b0 !
$end
#5000
b100000 0
1#
#10000
0#
#12000
0)
#15000
1#
#20000
0#
#25000
1#
#30000
0#
#35000
1#
#40000
b10111010101110101011101010111010 !
b10111010101110101011101010111010 /
b10101011101010111010101110101011 "
b10101011101010111010101110101011 .
0#
b111 (
b111 -
b11 '
b11 ,
#45000
1#
#50000
0#
#55000
1#
#60000
0#
b11111111111111111111111111111111 %
b11111111111111111111111111111111 +
1&
#65000
1#
#70000
0#
#75000
1#
#80000
b0 "
b0 .
0#
b0 '
b0 ,
#85000
1#
#90000
0#
#95000
1#
#100000
0#
b10101011110011011010101111001101 %
b10101011110011011010101111001101 +
b101 $
b101 *
0&
#105000
1#
#110000
0#
#115000
1#
#120000
0#
b101 '
b101 ,
#125000
1#
#130000
0#
#135000
1#
#140000
0#
b10101011110010101010101111001010 %
b10101011110010101010101111001010 +
1&
#145000
b10101011110010101010101111001010 "
b10101011110010101010101111001010 .
1#
#150000
0#
#155000
1#
#160000
0#
#165000
1#
#170000
0#
#175000
1#
#180000
b100010001000100010001000100010 !
b100010001000100010001000100010 /
b10001000100010001000100010001 "
b10001000100010001000100010001 .
0#
b10100 (
b10100 -
b1010 '
b1010 ,
#185000
1#
#190000
0#
#195000
1#
#200000
0#
b1000000010000000100000001 %
b1000000010000000100000001 +
b1000 $
b1000 *
#205000
1#
#210000
0#
#215000
1#
#220000
b1000000010000000100000001 "
b1000000010000000100000001 .
0#
b1000 '
b1000 ,
